<?xml version="1.0" encoding="utf-8"?>
<resources>
  <string name="accountPreferences" comment="Displayed on account screen, under the 'Profile' entry. This is for preferences synced with website on the server.">Préférences du compte</string>
  <string name="accountPreferencesHelp" comment="Help displayed on the account preferences screen.">Ces préférences sont appliquées à votre compte Lichess et seront utilisées sur tous les appareils.</string>
  <string name="allGames" comment="This is shown instead of 'Number of Games' if the number could not be loaded">Toutes les parties</string>
  <string name="areYouSure" comment="This is shown in confirmation dialogs.">Êtes-vous sûr ?</string>
  <string name="boardSettings" comment="This is shown in the app main settings screen, which opens a screen dedicated to chess board settings.">Paramètres de l\'échiquier</string>
  <string name="cancelTakebackOffer" comment="Menu action that cancels a previous takeback offer">Annuler la proposition de reprise du coup</string>
  <string name="clearButton" comment="Buttons that clear things, e.g. recent searches. Should be short.">Effacer</string>
  <string name="correspondenceClearSavedMove" comment="This is shown in the correspondence game screen. Will clear the saved move.">Effacer les coups enregistrés</string>
  <string name="customGameJoinAGame" comment="This is shown in the custom game screen. Will open the game lobby.">Joindre une partie</string>
  <string name="feedbackButton" comment="Shown in the settings, pressing this button will redirect to the lichess contact site.">Commentaires</string>
  <string name="goodEvening" comment="A greeting that is shown on the app's home page, e.g. 'Good evening, GM Magnus' (%s is substituted with the user's name). This is associated with a 'moon' icon and is displayed only between 18:00 and 06:00 local time. If the language you're translating into does not have this time based concept, just use a generic formula (like 'Hello' in english).">Bonsoir %s</string>
  <string name="goodEveningWithoutName" comment="A greeting that is shown on the app's home page, when the user is not logged in. This is associated with a 'moon' icon and is displayed only between 18:00 and 06:00 local time. If the language you're translating into does not have this time based concept, just use a generic formula (like 'Hello' in english).">Bonsoir</string>
  <string name="goodDay" comment="A greeting that is shown on the app's home page, e.g. 'Good day, GM Magnus' (%s is substituted with the user's name). This is associated with a 'sun' icon and is displayed only between 06:00 and 18:00 local time. If the language you're translating into does not have this time based concept, just use a generic formula (like 'Hello' in english).">Bonjour %s</string>
  <string name="goodDayWithoutName" comment="A greeting that is shown on the app's home page, when the user is not logged in. This is associated with a 'sun' icon and is displayed only between 06:00 and 18:00 local time. If the language you're translating into does not have this time based concept, just use a generic formula (like 'Hello' in english).">Bonjour</string>
  <string name="hideVariation" comment="Shown in the analysis screen.">Masquer les variantes</string>
  <string name="homeTab" comment="The tab in bottom navigation bar. Must be very short (10 characters max) to avoid ugly text shifting issues." maxLength="10">Accueil</string>
  <string name="liveStreamers" comment="This is shown as a heading in the streamer screen">Diffuseurs en direct</string>
  <string name="mustBeLoggedIn" comment="This is shown when the user tries to access a feature that requires login.">Vous devez être connecté pour voir cette page.</string>
  <string name="noSearchResults" comment="This is shown when the search did not return any results.">Aucun résultat</string>
  <string name="notAllFeaturesAreAvailable" comment="This is shown in the welcome message when the app is first installed">Prenez note que certaines fonctionnalités de l\'ancienne appli ou du site Web ne sont pas disponibles, mais nous ajoutons constamment des fonctionnalités.</string>
  <string name="notFollowingAnyUser" comment="This is shown in the list that contains user followed by the user. Displayed if the user does not follow any users.">Vous ne suivez aucune personne.</string>
  <string name="okButton" comment="This is used in varius confirmations dialogs. Translation should be short.">OK</string>
  <string name="overTheBoard" comment="Used in the main play menu to launch the Over the board game mode.">Jouer hors ligne avec un ami</string>
  <string name="playersMatchingSearchTerm" comment="This is shown when searching for a player. %s is the string that user entered in the search bar">Joueurs – \"%s\"</string>
  <string name="positionLeft" comment="Appears in the board settings screen to indicate clock position.">Côté gauche</string>
  <string name="positionRight" comment="Appears in the board settings screen to indicate clock position.">Côté droit</string>
  <string name="prefMagnifyDraggedPiece" comment="Title of a setting the settings screen. When enabled, the piece being dragged around the board will be magnified.">Grossir la pièce déplacée</string>
  <string name="puzzleStormConfirmEndRun" comment="Text of the confirmation dialog when ending a puzzle storm run">Voulez-vous mettre fin à cette série ?</string>
  <string name="puzzleStormFilterNothingToShow" comment="Shown when the user has no puzzles matching the filter criteria">Rien à afficher. Veuillez changer les filtres</string>
  <string name="puzzleStormNothingToShow" comment="Shown when the user has not played any puzzle storm runs yet. Prefer to not translate Puzzle Storm.">Rien à afficher. Jouez quelques séries de problèmes.</string>
  <string name="puzzleStormSubtitle" comment="Shown as a description for the 'Puzzle Storm' mode">Faites un maximum de problèmes en 3 minutes.</string>
  <string name="puzzleStreakAbortWarning" comment="Shown as a subtitle in the confirmation dialog for aborting puzzle streak. Prefer to not translate Puzzle Streak">Votre série actuelle prendra fin et votre résultat sera sauvegardé.</string>
  <string name="puzzleThemesSubtitle" comment="Shown as a description for the 'Puzzle themes' mode">Faites des problèmes basés sur vos ouvertures préférées ou choisissez un thème.</string>
  <string name="puzzlesTab" comment="The tab in bottom navigation bar. Must be very short (10 characters max) to avoid ugly text shifting issues." maxLength="10">Problèmes</string>
  <string name="recentSearches" comment="Title of the recent searches section in the search screen.">Recherches récentes</string>
  <string name="removeBookmark" comment="Label of the action of removing a game bookmark. Used in various places of the app where the space in constrained so this should remain short (eg: don't translate as 'Remove game bookmark', keep the essential).">Supprimer le favori</string>
  <string name="serverAnalysis" comment="Title of a switch in analysis settings, used to toggle the server analysis display.">Analyse par le serveur</string>
  <string name="settingsClockPosition" comment="Clock position entry in main settings screen.">Position de l\'horloge</string>
  <string name="settingsCustomBackgroundPresets" comment="Displayed on the custom background theme screen.">Préréglages</string>
  <string name="settingsDraggedPieceTarget" comment="Dragged piece target entry in main settings screen.">Cible de la pièce déplacée</string>
  <string name="settingsDraggedTargetCircle" comment="Dragged target settings circle type. One of the possible values of 'Dragged piece target' settings.">Cercle</string>
  <string name="settingsDraggedTargetSquare" comment="Dragged target settings square type. One of the possible values of 'Dragged piece target' settings.">Carré</string>
  <string name="settingsHomeWidgets" comment="Settings entry. Allow to enable which widgets are displayed on the home screen.">Widgets de l\'écran d\'accueil</string>
  <string name="settingsImmersiveMode" comment="Entry in the settings. When enabled, the app will hide the navigation bar and status bar.">Mode plein écran</string>
  <string name="settingsImmersiveModeSubtitle" comment="Subtitle for the 'Immersive Mode' setting. Gives an explanation of what the button does.">Masquer l\'interface utilisateur durant la partie. Utilisez cette option lorsque les gestes pour naviguer dans l\'interface utilisateur sur les bords de l\'écran vous gênent. S\'applique aux parties et aux problèmes.</string>
  <string name="settingsMaterialDifferenceCapturedPieces" comment="A value of the material difference settings choice (to show all captured pieces instead of material difference).">Pièces capturées</string>
  <string name="settingsPickAnImage" comment="Displayed in theme background choice screen, to allow user to pick and image from the image library as app custom background.">Sélectionner une image</string>
  <string name="settingsPickAnImageHelp" comment="Displayed in theme background choice screen, to help user pick an image.">L\'arrière-plan personnalisé ne fonctionne qu\'en mode sombre. Une image sombre est recommandée.</string>
  <string name="settingsPickAnImageBlur" comment="Displayed in theme background choice screen, to blur the chosen image.">Flouter l\'image</string>
  <string name="settingsPickAnImageHideBoard" comment="Displayed in theme background choice screen, to hide the board when viewing chosen image.">Cacher l\'échiquier</string>
  <string name="settingsPickAnImageShowBoard" comment="Displayed in theme background choice screen, to show the board when viewing chosen image.">Montrer l\'échiquier</string>
  <string name="settingsPickAnImageSwipeToDisplay" comment="Displayed in theme background choice screen, when viewing colors presets to display other colors backgrounds.">Glisser à gauche pour afficher les autres arrière-plans</string>
  <string name="settingsPieceShiftMethodEither" comment="A value of piece shift method settings entry.">Tapotez ou faites glisser</string>
  <string name="settingsPieceShiftMethodTapTwoSquares" comment="A value of piece shift method settings entry.">Tapotez deux cases</string>
  <string name="settingsShapeDrawing" comment="Entry in the settings.">Dessin de forme</string>
  <string name="settingsShapeDrawingSubtitle" comment="Help message for the 'Shape drawing' settings entry.">Dessinez des formes à l\'aide de deux doigts : maintenez un doigt sur une case vide et faites glisser un autre doigt pour dessiner une forme.</string>
  <string name="settingsShowBorder" comment="Settings found in theme screen. If enabled a border will be shown around the board.">Afficher la bordure</string>
  <string name="settingsTouchFeedback" comment="Entry in the settings. When enabled, the app will vibrate on some game events like move and capture.">Retour tactile</string>
  <string name="settingsTouchFeedbackSubtitle" comment="Help message for the touch feedback settings entry in main settings screen.">Lorsque cette option est activée, l\'appareil vibrera lorsque vous bougez ou capturez une pièce.</string>
  <string name="settingsTab" comment="The tab in bottom navigation bar. Must be very short (10 characters max) to avoid ugly text shifting issues." maxLength="10">Paramètres</string>
  <string name="shareGamePGN" comment="Menu action that shares the PGN of a game">Partager le PGN</string>
  <string name="shareGameURL" comment="Menu action that shares the URL of the current game">Partager l\'URL de la partie</string>
  <string name="sharePositionAsFEN" comment="Menu action that shares the current position as a FEN string">Partager la position FEN</string>
  <string name="sharePuzzle" comment="This is shown in the puzzle screen. When pressed, the user can share the puzzle.">Partager ce problème</string>
  <string name="showComments" comment="Shown in the analysis screen.">Afficher les commentaires</string>
  <string name="showResult" comment="This is the label of a button in the bottom bar shown when viewing a game from your history. Pressing the button will open a dialog showing the game's result (e.g 'White resigned') and displaying button such as 'new opponent'">Afficher le résultat</string>
  <string name="showVariations" comment="Shown in the analysis screen.">Afficher les variantes</string>
  <string name="somethingWentWrong" comment="This is a generic text to be shown when something unexpected happens, e.g. failing to load data from the server.">Une erreur s\'est produite.</string>
  <string name="systemColors" comment="The title of the system colors setting. When enabling this, tha app's colors will match those of the operating system.">Couleurs du système</string>
  <string name="theme" comment="Graphic theme section in the global app settings.">Thème</string>
  <string name="toolsTab" comment="The tab in bottom navigation bar. Must be very short (10 characters max) to avoid ugly text shifting issues. Currently this includes the analysis board, the chess clock, and importing a position by PGN/FEN" maxLength="10">Outils</string>
  <string name="unsupportedVariant" comment="Shown when trying to access/play a variant not yet supported in the app.">La variante %s n\'est pas prise en charge par cette version.</string>
  <string name="waitingForOpponentToJoin" comment="This is after the user has created a game and is waiting for an opponent to join.">En attente d\'un adversaire...</string>
  <string name="watchTab" comment="The tab in bottom navigation bar. Must be very short (10 characters max) to avoid ugly text shifting issues." maxLength="10">Regarder</string>
  <string name="welcomeToLichessApp" comment="A welcome message shown only the first time the app is installed.">Bienvenue dans l\'application Lichess !</string>
  <string name="viewGame" comment="Button text in puzzle settings to view the originating game.">Voir la partie</string>
  <string name="customizeHomeTip" comment="Shown in a widget on the home screen to let the user know that they can customize their homescreen">Astuce : Vous pouvez ajouter des widgets à l\'écran d\'accueil ou supprimer ceux dont vous n\'avez pas besoin.</string>
  <string name="customizeHomeTipDismiss" comment="Hides the widget to customize the home screen.">Ignorer</string>
  <string name="customizeButton" comment="Text of a button, so translation should be short.">Personnaliser</string>
  <string name="stopShowingThreat" comment="This disables the 'Show Treat' mode in analysis.">Ne pas afficher la menace</string>
  <string name="tournamentCompleted" comment="Title of a tab in the tournament screen, showing tournaments that are already completed. Translation should be short ideally one word">Terminé</string>
  <string name="tournamentJumpToMyPage" comment="Accessibility description of a button that jumps to user's position in tournament standings">Aller à ma page</string>
  <string name="displayModeDetailed" comment="">Affichage détaillé</string>
  <string name="openingExplorerNotAvailableOffline" comment="">L\'explorateur d\'ouvertures n\'est pas accessible hors ligne.</string>
  <string name="challengeCreated" comment="Shown as a bottom banner when another player has been challenged.">Défi créé : Vous recevrez une notification lorsque la partie commencera.\nVous pouvez y accéder depuis l’onglet Accueil.</string>
  <string name="previousPage" comment="Shows the previous page, e.g. in tournament standings">Précédent</string>
</resources>
